broly/__init__.py
broly/column.py
broly/model.py
broly-0.4.8.dist-info/METADATA
broly-0.4.8.dist-info/WHEEL
broly-0.4.8.dist-info/top_level.txt
broly-0.4.8.dist-info/RECORD
