Metadata-Version: 2.1
Name: broly
Version: 0.4.8
Summary: small (wip) wrapper for rds data api for lambda
Home-page: https://github.com/lucasmarcelli/broly/
Author: Lucas Marcelli
Author-email: lucas@marcelli.ca
License: UNKNOWN
Project-URL: Source, https://github.com/lucasmarcelli/broly/
Keywords: lambda,setuptools,development,rds-data,wip
Platform: UNKNOWN
Classifier: Development Status :: 3 - Alpha
Classifier: Intended Audience :: Developers
Classifier: License :: OSI Approved :: MIT License
Classifier: Programming Language :: Python :: 3
Classifier: Programming Language :: Python :: 3.5
Classifier: Programming Language :: Python :: 3.6
Classifier: Programming Language :: Python :: 3.7
Classifier: Programming Language :: Python :: 3.8
Classifier: Programming Language :: Python :: 3 :: Only
Requires-Python: >=3.5, <4
Requires-Dist: pypika
